khloraascaf/__init__.py
khloraascaf/__main__.py
khloraascaf/assembly_graph.py
khloraascaf/cli.py
khloraascaf/exceptions.py
khloraascaf/inputs.py
khloraascaf/lib.py
khloraascaf/multiplied_doubled_contig_graph.py
khloraascaf/outputs.py
khloraascaf/py.typed
khloraascaf/result.py
khloraascaf/run_metadata.py
khloraascaf/scaffolding_methods.py
khloraascaf/utils_debug.py
khloraascaf/ilp/__init__.py
khloraascaf/ilp/dirf_sets.py
khloraascaf/ilp/invf_sets.py
khloraascaf/ilp/pulp_circuit.py
khloraascaf/ilp/pulp_max_dirf.py
khloraascaf/ilp/pulp_max_invf.py
khloraascaf/ilp/pulp_max_presscore.py
khloraascaf/ilp/pulp_repeated_fragments.py
khloraascaf/ilp/pulp_to_solver.py
khloraascaf/ilp/pulp_var_db.py
khloraascaf-1.10.0.dist-info/LICENCE
khloraascaf-1.10.0.dist-info/METADATA
khloraascaf-1.10.0.dist-info/WHEEL
khloraascaf-1.10.0.dist-info/top_level.txt
khloraascaf-1.10.0.dist-info/RECORD
