Metadata-Version: 2.1
Name: khloraascaf
Version: 1.10.0
Summary: A python package that takes an assembly result of a chloroplast genome and continues it by computing the scaffolding stage.
Author-email: vepain <victor.epain@laposte.net>
License: ### GNU GENERAL PUBLIC LICENSE
Project-URL: Homepage, https://gitlab.com/khloraa_scaffolding/khloraa_scaffolding
Project-URL: Repository, https://gitlab.com/khloraa_scaffolding/khloraa_scaffolding
Project-URL: Documentation, https://khloraa-scaffolding.readthedocs.io
Project-URL: Changelog, https://khloraa-scaffolding.readthedocs.io/en/latest/changelog.html
Keywords: Scaffolding,Chloroplast,Assembly,DNA repeats
Classifier: Development Status :: 5 - Production/Stable
Classifier: Intended Audience :: Developers
Classifier: License :: OSI Approved :: GNU General Public License v3 or later (GPLv3+)
Classifier: Operating System :: Unix
Classifier: Programming Language :: Python :: 3.9
Classifier: Topic :: Software Development :: Libraries :: Python Modules
Requires-Python: >=3.9
License-File: LICENCE
Requires-Dist: bitarray (<2.5.0,>=2.4.0)
Requires-Dist: pulp (<2.8,>=2.7)
Requires-Dist: revsymg (<0.5.0,>=0.4.1)
Requires-Dist: PyYAML (<6.1,>=6.0)
